quber_workflow/__init__.py
quber_workflow/cli.py
quber_workflow/py.typed
quber_workflow/version.py
quber_workflow/commands/__init__.py
quber_workflow/commands/init.py
quber_workflow/commands/migrate.py
quber_workflow/commands/update.py
quber_workflow/templates/agents/github-workflow.md
quber_workflow/templates/agents/jira-workflow.md
quber_workflow/templates/docs/GITHUB_WORKFLOW_SPEC.md
quber_workflow/templates/docs/ISSUES_SPEC.md
quber_workflow/templates/docs/PR_EVIDENCE_CHECKLIST.md
quber_workflow/templates/docs/PR_EVIDENCE_GUIDELINES.md
quber_workflow/templates/github-workflows/jira-transition.yml
quber_workflow/templates/skills/github-operations/SKILL.md
quber_workflow/templates/skills/github-operations/scripts/create-pr.sh
quber_workflow/templates/skills/github-operations/scripts/get-pr-files.sh
quber_workflow/templates/skills/github-operations/scripts/get-pr.sh
quber_workflow/templates/skills/github-operations/scripts/list-prs.sh
quber_workflow/templates/skills/jira-operations/SKILL.md
quber_workflow/templates/skills/jira-operations/scripts/add-comment.sh
quber_workflow/templates/skills/jira-operations/scripts/create-issue.sh
quber_workflow/templates/skills/jira-operations/scripts/delete-issue.sh
quber_workflow/templates/skills/jira-operations/scripts/get-issue-types.sh
quber_workflow/templates/skills/jira-operations/scripts/get-issue.sh
quber_workflow/templates/skills/jira-operations/scripts/get-transitions.sh
quber_workflow/templates/skills/jira-operations/scripts/search-issues.sh
quber_workflow/templates/skills/jira-operations/scripts/transition-issue.sh
quber_workflow/templates/skills/jira-operations/scripts/update-issue.sh
quber_workflow-0.1.0.dist-info/METADATA
quber_workflow-0.1.0.dist-info/WHEEL
quber_workflow-0.1.0.dist-info/entry_points.txt
quber_workflow-0.1.0.dist-info/RECORD
